MANIFEST.in
README.md
requirements.txt
setup.cfg
setup.py
shandlers/__init__.py
shandlers/logger.py
shandlers.egg-info/PKG-INFO
shandlers.egg-info/SOURCES.txt
shandlers.egg-info/dependency_links.txt
shandlers.egg-info/requires.txt
shandlers.egg-info/top_level.txt
shandlers/sqs/__init__.py
shandlers/sqs/exceptions.py
shandlers/sqs/handler.py
shandlers/sqs/schema.py
tests/__init__.py
tests/sqs_handler_test.py