Metadata-Version: 2.1
Name: shandlers
Version: 0.0.2
Summary: A python lib that provides handlers for serverless events
Home-page: https://github.com/GonzaloSaad/shandlers
Author: GonzaloSaad
Author-email: saad.gonzalo.ale@gmail.com
License: UNKNOWN
Keywords: python aws serverless
Platform: UNKNOWN
Classifier: Intended Audience :: Developers
Classifier: Operating System :: OS Independent
Classifier: Programming Language :: Python :: 3
Classifier: License :: OSI Approved :: MIT License
